ml_utils_jme45/__about__.py
ml_utils_jme45/__init__.py
ml_utils_jme45/ml_utils.py
ml_utils_jme45-0.2.0.dist-info/METADATA
ml_utils_jme45-0.2.0.dist-info/WHEEL
ml_utils_jme45-0.2.0.dist-info/licenses/LICENSE
ml_utils_jme45-0.2.0.dist-info/RECORD
